ehyd_tools/__init__.py
ehyd_tools/__main__.py
ehyd_tools/_console_script.py
ehyd_tools/_reader_alt.py
ehyd_tools/data_processing.py
ehyd_tools/design_rainfall.py
ehyd_tools/ehyd_stations.json
ehyd_tools/in_out.py
ehyd_tools/niederschl_lufttemp_verdunst.csv
ehyd_tools/niederschl_lufttemp_verdunst_2014.csv
ehyd_tools/oberflaechenwasser.csv
ehyd_tools/sww_utils.py
ehyd_tools/synthetic_rainseries.py
ehyd_tools/synthetic_rainseries_v0.py
ehyd_tools/unteririsches_wasser.csv
ehyd_tools-0.1.8.dist-info/licenses/LICENSE
ehyd_tools-0.1.8.dist-info/METADATA
ehyd_tools-0.1.8.dist-info/WHEEL
ehyd_tools-0.1.8.dist-info/entry_points.txt
ehyd_tools-0.1.8.dist-info/top_level.txt
ehyd_tools-0.1.8.dist-info/RECORD
