Metadata-Version: 2.4
Name: ehyd-tools
Version: 0.1.8
Summary: Reading and analyzing hydro(geo)logic time series from the Austrian government's "ehyd.gv.at" platform.
Author-email: Markus Pichler <markus.pichler@tugraz.at>
License: MIT
Project-URL: Changelog, https://github.com/MarkusPic/ehyd_tools/blob/master/CHANGELOG.md
Project-URL: homepage, https://github.com/MarkusPic/ehyd_tools
Project-URL: funding, https://www.buymeacoffee.com/MarkusP
Keywords: austria,precipitation,groundwater,hydrology,data,environment,civil_engineering,api
Classifier: Programming Language :: Python :: 3
Classifier: License :: OSI Approved :: MIT License
Classifier: Operating System :: OS Independent
Classifier: Development Status :: 4 - Beta
Classifier: Natural Language :: English
Classifier: Topic :: Scientific/Engineering
Classifier: Topic :: Scientific/Engineering :: Hydrology
Classifier: Intended Audience :: Science/Research
Requires-Python: >=3.7
License-File: LICENSE
Requires-Dist: numpy>=1.14
Requires-Dist: pandas>=1
Requires-Dist: matplotlib>=3
Requires-Dist: requests
Requires-Dist: argh
Provides-Extra: parquet
Requires-Dist: fastparquet; extra == "parquet"
Requires-Dist: pyarrow; extra == "parquet"
Dynamic: license-file
